[
    {
        "pergunta": "Quais jogadores aceleraram o ritmo do jogo contra o Ceará, no dia 1 de abril de 2023, com suas arrancadas e dribles?",
        "perfil": "Preparador Físico",
        "dados_personareact": "{\n  'Calebe': 0.014235693686514358,\n  'Yago Pikachu': 0.013949646426982142,\n  'Emanuel Britez': 0.0045607864370319435,\n  'Hercules': 0.0012585157301782462,\n  'Tinga': -0.006362479121340499,\n  'Bruno Pacheco': -0.007713032315664035,\n  'Thiago Galhardo': -0.008147734802436562,\n  'Romarinho': -0.010116108895350851,\n  'Titi': -0.010680821071501449,\n  'Lucas Sasha': -0.010960122803398658,\n  'Moises Vieira': -0.011801119470219406,\n  'Tomas Pochettino': -0.042664501677647744,\n  'Juan Martin Lucero': -0.05088090245128581,\n  'Caio': -0.05352060188806162\n}",
        "resposta_personareact": "Após análise do desempenho no jogo contra o Ceará, realizado em 1 de abril de 2023, os jogadores que efetivamente aceleraram o ritmo da partida foram Calebe e Yago Pikachu. Ambos se destacaram significativamente, apresentando métricas de impacto positivas com 0.0142 e 0.0139, respectivamente. \n\nEssas métricas indicam que Calebe e Yago Pikachu não apenas realizaram arrancadas e dribles, mas também conseguiram influenciar o fluxo de jogo de maneira ofensiva, contribuindo para a dinâmica da equipe. \n\nOutros jogadores como Emanuel Britez também tiveram uma contribuição, mas em uma escala menor, com um impacto de 0.0046. Para maximizar o desempenho em campo, seria interessante analisar como as características físicas e técnicas desses jogadores podem ser potencializadas em treinos específicos. \n\nConsiderando o perfil de preparador físico, essas informações são cruciais para ajustar estratégias e melhorar a performance da equipe em futuros desafios.",
        "dados_react": "{\n  'Calebe': {\n    'Media_Aceleracao': 0.014235693686514358,\n    'Media_Velocidade': 1.1722246995564352\n  },\n  'Yago Pikachu': {\n    'Media_Aceleracao': 0.013949646426982142,\n    'Media_Velocidade': 1.2044081145543035\n  },\n  'Emanuel Britez': {\n    'Media_Aceleracao': 0.0045607864370319435,\n    'Media_Velocidade': 0.9905784177643863\n  },\n  'Hercules': {\n    'Media_Aceleracao': 0.0012585157301782462,\n    'Media_Velocidade': 0.9121159643787028\n  },\n  'Tinga': {\n    'Media_Aceleracao': -0.006362479121340499,\n    'Media_Velocidade': 1.1740420544489376\n  },\n  'Bruno Pacheco': {\n    'Media_Aceleracao': -0.007713032315664035,\n    'Media_Velocidade': 1.3622634444889454\n  },\n  'Thiago Galhardo': {\n    'Media_Aceleracao': -0.008147734802436562,\n    'Media_Velocidade': 1.0475018072009474\n  },\n  'Romarinho': {\n    'Media_Aceleracao': -0.010116108895350851,\n    'Media_Velocidade': 0.9996514409700152\n  },\n  'Titi': {\n    'Media_Aceleracao': -0.010680821071501449,\n    'Media_Velocidade': 0.9360252244741523\n  },\n  'Lucas Sasha': {\n    'Media_Aceleracao': -0.010960122803398658,\n    'Media_Velocidade': 1.3904642100355726\n  },\n  'Moises Vieira': {\n    'Media_Aceleracao': -0.011801119470219406,\n    'Media_Velocidade': 1.05104900322245\n  },\n  'Tomas Pochettino': {\n    'Media_Aceleracao': -0.042664501677647744,\n    'Media_Velocidade': 1.9444537590902835\n  },\n  'Juan Martin Lucero': {\n    'Media_Aceleracao': -0.05088090245128581,\n    'Media_Velocidade': 1.4548611994591851\n  },\n  'Caio': {\n    'Media_Aceleracao': -0.05352060188806162,\n    'Media_Velocidade': 1.1601313980844454\n  }\n}",
        "resposta_react_prompt": "Os jogadores que aceleraram o ritmo do jogo contra o Ceará, no dia 1 de abril de 2023, foram Calebe e Yago Pikachu. Calebe teve uma média de aceleração de 0.0142 e uma média de velocidade de 1.1722, enquanto Yago Pikachu teve uma média de aceleração de 0.0139 e uma média de velocidade de 1.2044. Esses dados são importantes para um preparador físico, pois indicam a capacidade de explosão e velocidade dos atletas."
    }
]
